Metadata-Version: 1.1
Name: narcissujsk
Version: 0.0.1
Summary: desc
Home-page: https://github.com/narcissujsk/narcissujsk
Author: narcissujsk
Author-email: happiness1019@gmail.com
License: MIT
Keywords: narcissujsk
Platform: UNKNOWN
Classifier: License :: OSI Approved :: MIT License
Classifier: Programming Language :: Python
Classifier: Intended Audience :: Developers
Classifier: Operating System :: OS Independent
